robeex_ai_drone_api/.gitignore
robeex_ai_drone_api/__init__.py
robeex_ai_drone_api/__main__.py
robeex_ai_drone_api/ai_drone.py
robeex_ai_drone_api/bottom_flash_led_api.py
robeex_ai_drone_api/nav_api.py
robeex_ai_drone_api/rc_api.py
robeex_ai_drone_api/rgb_led_api.py
robeex_ai_drone_api/utils.py
robeex_ai_drone_api/vec2.py
robeex_ai_drone_api/video_api.py
robeex_ai_drone_api-0.2.10.dist-info/METADATA
robeex_ai_drone_api-0.2.10.dist-info/WHEEL
robeex_ai_drone_api-0.2.10.dist-info/licenses/LICENSE.md
robeex_ai_drone_api-0.2.10.dist-info/RECORD
