Metadata-Version: 2.4
Name: robeex-ai-drone-api
Version: 0.2.10
Summary: A Python library designed to control and interact with RoBeeX AI Drones
License-Expression: MIT
License-File: LICENSE.md
Author: RoBeeX Robotics
Author-email: robeex.robotics@gmail.com
Requires-Python: >=3.11
Classifier: Programming Language :: Python :: 3
Classifier: Programming Language :: Python :: 3.11
Classifier: Programming Language :: Python :: 3.12
Classifier: Programming Language :: Python :: 3.13
Classifier: Programming Language :: Python :: 3.14
Project-URL: Homepage, https://robeex.com/?utm_source=pypi
